kaigara/__init__.py
kaigara/base.py
kaigara/model/__init__.py
kaigara/model/_growing_tube_model.py
kaigara/model/_raup_model.py
kaigara-0.0.1a9.dist-info/LICENSE
kaigara-0.0.1a9.dist-info/WHEEL
kaigara-0.0.1a9.dist-info/METADATA
kaigara-0.0.1a9.dist-info/RECORD
