Metadata-Version: 2.1
Name: kaigara
Version: 0.0.1a9
Summary: 
Home-page: https://github.com/noshita/kaigara
License: ISC
Keywords: theoretical morphology,malacology
Author: Noshita, Koji
Author-email: noshita@morphometrics.jp
Requires-Python: >=3.7.10,<4.0
Classifier: Intended Audience :: Developers
Classifier: Intended Audience :: Science/Research
Classifier: License :: OSI Approved
Classifier: License :: OSI Approved :: ISC License (ISCL)
Classifier: Operating System :: MacOS
Classifier: Operating System :: Microsoft :: Windows
Classifier: Operating System :: POSIX
Classifier: Operating System :: Unix
Classifier: Programming Language :: Python
Classifier: Programming Language :: Python :: 3
Classifier: Programming Language :: Python :: 3.7
Classifier: Programming Language :: Python :: 3.8
Classifier: Programming Language :: Python :: 3.9
Classifier: Topic :: Scientific/Engineering
Classifier: Topic :: Software Development
Requires-Dist: numpy (>=1.19.5,<2.0.0)
Requires-Dist: scipy (>=1.4.1,<2.0.0)
Requires-Dist: sympy (>=1.7,<2.0)
Project-URL: Repository, https://github.com/noshita/kaigara
